mro_tools/__init__.py
mro_tools/__main__.py
mro_tools/klass.py
mro_tools/method.py
mro_tools/render.py
mro_tools/utils.py
mro_tools/version.py
mro_tools-0.3.0.dist-info/AUTHORS.rst
mro_tools-0.3.0.dist-info/LICENSE.rst
mro_tools-0.3.0.dist-info/METADATA
mro_tools-0.3.0.dist-info/WHEEL
mro_tools-0.3.0.dist-info/entry_points.txt
mro_tools-0.3.0.dist-info/top_level.txt
mro_tools-0.3.0.dist-info/RECORD
