Metadata-Version: 2.1
Name: mro-tools
Version: 0.3.0
Summary: Various cli tools related to MRO. Useful for debugging complex class strictures.
Home-page: https://github.com/miki725/mro-tools
Author: Miroslav Shubernetskiy
Author-email: UNKNOWN
License: MIT
Keywords: mro
Platform: UNKNOWN
Classifier: Intended Audience :: Developers
Classifier: Natural Language :: English
Classifier: License :: OSI Approved :: MIT License
Classifier: Programming Language :: Python
Classifier: Programming Language :: Python :: 2.7
Classifier: Programming Language :: Python :: 3
Classifier: Programming Language :: Python :: 3.6
Classifier: Development Status :: 2 - Pre-Alpha
Requires-Dist: click
Requires-Dist: pygments
Requires-Dist: setuptools
